test_travis/__init__.py
test_travis/main.py
test_travis-0.1.1.dist-info/entry_points.txt
test_travis-0.1.1.dist-info/LICENSE
test_travis-0.1.1.dist-info/WHEEL
test_travis-0.1.1.dist-info/METADATA
test_travis-0.1.1.dist-info/RECORD
