Metadata-Version: 2.1
Name: test-travis
Version: 0.1.1
Summary: A cookiecutter template for Python project
Home-page: https://github.com/lin-zone/test_travis
License: MIT
Keywords: packaging,dependency,poetry,setuptools,pip
Author: lin-zone
Author-email: z_one10@163.com
Requires-Python: >=3.6,<4.0
Classifier: License :: OSI Approved :: MIT License
Classifier: Programming Language :: Python :: 3
Classifier: Programming Language :: Python :: 3.6
Classifier: Programming Language :: Python :: 3.7
Classifier: Programming Language :: Python :: 3.8
Requires-Dist: autopep8
Requires-Dist: jinja2
Requires-Dist: poetry
Project-URL: Repository, https://github.com/lin-zone/test_travis
